{
"companyName": "Mofunzone",
"productName": "Duck Life: Space",
"dataUrl": "WebGLPoki.data.unityweb?v=1",
"asmCodeUrl": "WebGLPoki.asm.code.unityweb?v=1",
"asmMemoryUrl": "WebGLPoki.asm.memory.unityweb?v=1",
"asmFrameworkUrl": "WebGLPoki.asm.framework.unityweb?v=1",
"TOTAL_MEMORY": 536870912,
"graphicsAPI": ["WebGL 2.0", "WebGL 1.0"],
"webglContextAttributes": {"preserveDrawingBuffer": false},
"splashScreenStyle": "Dark",
"backgroundColor": "#231F20",
"cacheControl": {"dataUrl": "must-revalidate"}
}